hcrystalball/__init__.py
hcrystalball/exceptions.py
hcrystalball/utils.py
hcrystalball/compose/__init__.py
hcrystalball/compose/_ts_column_transformer.py
hcrystalball/data/rossmann_train_rich_top_100.csv
hcrystalball/ensemble/__init__.py
hcrystalball/ensemble/_simple_ensemble.py
hcrystalball/ensemble/_stacking_ensemble.py
hcrystalball/feature_extraction/__init__.py
hcrystalball/feature_extraction/_holiday_transformer.py
hcrystalball/feature_extraction/_seasonal_transformer.py
hcrystalball/metrics/__init__.py
hcrystalball/metrics/_scorer.py
hcrystalball/model_selection/__init__.py
hcrystalball/model_selection/_configuration.py
hcrystalball/model_selection/_data_preparation.py
hcrystalball/model_selection/_large_scale_cross_validation.py
hcrystalball/model_selection/_model_selector.py
hcrystalball/model_selection/_model_selector_result.py
hcrystalball/model_selection/_split.py
hcrystalball/model_selection/utils.py
hcrystalball/preprocessing/__init__.py
hcrystalball/preprocessing/_endog_transformer.py
hcrystalball/wrappers/__init__.py
hcrystalball/wrappers/_base.py
hcrystalball/wrappers/_prophet.py
hcrystalball/wrappers/_sarimax.py
hcrystalball/wrappers/_sklearn.py
hcrystalball/wrappers/_statsmodels.py
hcrystalball/wrappers/_tbats.py
hcrystalball-0.1.12.dist-info/AUTHORS.rst
hcrystalball-0.1.12.dist-info/LICENSE.txt
hcrystalball-0.1.12.dist-info/METADATA
hcrystalball-0.1.12.dist-info/WHEEL
hcrystalball-0.1.12.dist-info/top_level.txt
hcrystalball-0.1.12.dist-info/RECORD
